coinpulse/__init__.py
coinpulse/client.py
coinpulse/exceptions.py
coinpulse/models.py
coinpulse-0.1.0.dist-info/licenses/LICENSE
coinpulse-0.1.0.dist-info/METADATA
coinpulse-0.1.0.dist-info/WHEEL
coinpulse-0.1.0.dist-info/top_level.txt
coinpulse-0.1.0.dist-info/RECORD
