Metadata-Version: 2.4
Name: coinpulse
Version: 0.1.0
Summary: Simple Python SDK for the CoinPulse crypto portfolio API
Home-page: https://github.com/soutone/coinpulse-python
Author: CoinPulse
Author-email: CoinPulse <hello@coinpulse.dev>
License: MIT
Project-URL: Homepage, https://coinpulse.dev
Project-URL: Documentation, https://coinpulse.dev/docs
Project-URL: Repository, https://github.com/soutone/coinpulse-python
Project-URL: Issues, https://github.com/soutone/coinpulse-python/issues
Keywords: crypto,cryptocurrency,bitcoin,ethereum,portfolio,api,sdk
Classifier: Development Status :: 4 - Beta
Classifier: Intended Audience :: Developers
Classifier: License :: OSI Approved :: MIT License
Classifier: Operating System :: OS Independent
Classifier: Programming Language :: Python :: 3
Classifier: Programming Language :: Python :: 3.10
Classifier: Programming Language :: Python :: 3.11
Classifier: Programming Language :: Python :: 3.12
Classifier: Topic :: Office/Business :: Financial :: Investment
Classifier: Topic :: Software Development :: Libraries :: Python Modules
Requires-Python: >=3.10
License-File: LICENSE
Requires-Dist: requests>=2.28.0
Provides-Extra: dev
Requires-Dist: pytest>=7.0.0; extra == "dev"
Requires-Dist: pytest-cov>=4.0.0; extra == "dev"
Requires-Dist: black>=23.0.0; extra == "dev"
Requires-Dist: mypy>=1.0.0; extra == "dev"
Requires-Dist: types-requests>=2.28.0; extra == "dev"
Dynamic: author
Dynamic: home-page
Dynamic: license-file
Dynamic: requires-python
